[
    {
        "threshold": [
            null
        ],
        "rules": [
            0,
            0,
            0,
            0,
            0
        ]
    },
    {
        "threshold": [
            1,
            6000
        ],
        "rules": [
            0,
            0,
            0,
            0,
            null
        ]
    },
    {
        "threshold": [
            6001,
            21600
        ],
        "rules": [
            0,
            0,
            0.17,
            1,
            6000
        ]
    },
    {
        "threshold": [
            21601,
            52000
        ],
        "rules": [
            0,
            2652,
            0.3,
            1,
            21600
        ]
    },
    {
        "threshold": [
            52001,
            62500
        ],
        "rules": [
            0,
            11772,
            0.42,
            1,
            52000
        ]
    },
    {
        "threshold": [
            62501
        ],
        "rules": [
            0,
            16182,
            0.47,
            1,
            62500
        ]
    }
]